{
    "job_title": "Business Development Manager",
    "salary": "Cạnh tranh",
    "city": "Hồ Chí Minh~",
    "experience": "",
    "work_location": "No. 126, B2 Street, Sala Urban Area, An Loi Dong Ward, Thu Duc City, Ho Chi Minh City",
    "expiration_date": "",
    "company_name": "",
    "company_address": "No. 126, B2 Street, Sala Urban Area, An Loi Dong Ward, Thu Duc City, Ho Chi Minh City",
    "position_level": "Quản lý",
    "job_type": "Nhân viên chính thức~",
    "skills": "Quản lý kinh doanh khu vực~Area Sales Manager Out of home channel~Senior Group Account Manager~Account Director~Business Director~Area Account Supervisor~ETC Supervisor~Trưởng bán hàng vùng~Quản lý khu vực ASM toàn quốc~Điều hành kinh doanh",
    "job_fields": "",
    "number_of_vacancies": "Nothing",
    "gender": "Nothing",
    "company_field": "Nothing",
    "company_size": "Nothing",
    "work_hours": "Nothing",
    "job_description": "",
    "requirements": "",
    "benefits": "",
    "html_name": "business-development-manager.35C1D2DA.html",
    "web_name": "careerviet"
}